{
    "domain": ".s3.us-west-2.amazonaws.com",
    "owner": {
        "name": "Amazon Technologies, Inc.",
        "displayName": "Amazon.com",
        "privacyPolicy": "https://www.amazon.com/gp/help/customer/display.html?nodeId=468496",
        "url": "http://amazon.com"
    },
    "source": [
        "DuckDuckGo-AU"
    ],
    "prevalence": 0.000201,
    "sites": 2,
    "subdomains": [],
    "cnames": [],
    "fingerprinting": 2,
    "resources": [
        {
            "rule": "\\.s3\\.us-west-2\\.amazonaws\\.com\\/stamped\\.io\\/uploads\\/account\\/302255\\/meta\\/launcher_logo_image\\.jpg",
            "cookies": 0,
            "fingerprinting": 0,
            "subdomains": [],
            "apis": {},
            "sites": 2,
            "prevalence": 0.000201,
            "cnames": [],
            "responseHashes": [
                "4eb5f26b31b1c4d4277990cc5a01423f80f4cbf86300ae7b85ac45f41c1c5ffd"
            ],
            "type": "Image",
            "firstPartyCookies": {},
            "firstPartyCookiesSent": {},
            "exampleSites": [
                "stfrock.com.au",
                "www.stfrock.com.au"
            ]
        }
    ],
    "categories": [
        "CDN"
    ],
    "performance": {},
    "cookies": 0,
    "topInitiators": [
        {
            "domain": "ajax.googleapis.com",
            "prevalence": 0.75
        },
        {
            "domain": "googletagmanager.com",
            "prevalence": 0.25
        }
    ],
    "types": {
        "Image": 2
    },
    "nameservers": []
}