{
    "domain": "a-mx.com",
    "owner": {
        "name": "Monet Engine Inc.",
        "displayName": "Monet Engine"
    },
    "source": [
        "DuckDuckGo-CA"
    ],
    "prevalence": 0.0214,
    "sites": 212,
    "subdomains": [
        "id"
    ],
    "cnames": [],
    "fingerprinting": 0,
    "resources": [
        {
            "rule": "a-mx\\.com\\/sync\\/",
            "cookies": 0.00443,
            "fingerprinting": 0,
            "subdomains": [
                "id"
            ],
            "apis": {},
            "sites": 57,
            "prevalence": 0.00574,
            "cnames": [],
            "responseHashes": [
                "a544d4a3bebb472dc53f5f95d825c45a8c7a239e6afaa444f982aa984e15c67d"
            ],
            "type": "Fetch",
            "firstPartyCookies": {},
            "firstPartyCookiesSent": {
                "lotame_domain_check": 0.004432356200261912,
                "_li_dcdm_c": 0.0005036768409388536,
                "lp_59211": 0.00010073536818777072,
                "dnsDisplayed": 0.00010073536818777072,
                "signedLspa": 0.00010073536818777072,
                "_uc_referrer": 0.00010073536818777072
            },
            "exampleSites": [
                "drudgereport.com",
                "pastebin.com",
                "screenrant.com",
                "www.howtogeek.com",
                "www.newsweek.com",
                "www.pcworld.com",
                "www.dualshockers.com",
                "segmentnext.com",
                "basketball.realgm.com",
                "www.gpucheck.com",
                "www.thethings.com",
                "www.wikifeet.com",
                "downloads.digitaltrends.com",
                "www.audiokarma.org",
                "www.gbmb.org",
                "www.postgresqltutorial.com",
                "www.babelio.com",
                "www.usmagazine.com",
                "www.closerweekly.com",
                "yesichat.com"
            ]
        },
        {
            "rule": "a-mx\\.com\\/sync",
            "cookies": 0.00272,
            "fingerprinting": 0,
            "subdomains": [
                "id"
            ],
            "apis": {},
            "sites": 28,
            "prevalence": 0.00282,
            "cnames": [],
            "responseHashes": [
                "015ec8625b9792df07618b0f07da76378ceabfcbb2a14648298f1e9a403b4e44",
                "134518472d9e9e110619e27b0d91384ae81f6087c3658eb7596f9dd78d12d7fd"
            ],
            "type": "Fetch",
            "firstPartyCookies": {},
            "firstPartyCookiesSent": {
                "lotame_domain_check": 0.001108089050065478,
                "_li_dcdm_c": 0.00020147073637554144
            },
            "exampleSites": [
                "healthfully.com",
                "www.mid-day.com",
                "dermnetnz.org",
                "timesofindia.indiatimes.com",
                "www.genealogy.com",
                "www.picuki.com",
                "www.hitc.com",
                "macleans.ca",
                "www.thinkbabynames.com",
                "iplocation.io",
                "www.dailyfaceoff.com",
                "www.metrotimes.com",
                "thetvdb.com",
                "monsterhunter.fandom.com",
                "bdocodex.com",
                "rokslide.com",
                "spy.com",
                "www.scotsman.com",
                "faroutmagazine.co.uk",
                "aviewfrommyseat.com"
            ]
        },
        {
            "rule": "a-mx\\.com\\/u",
            "cookies": 0.0147,
            "fingerprinting": 0,
            "subdomains": [
                "id"
            ],
            "apis": {},
            "sites": 163,
            "prevalence": 0.0164,
            "cnames": [],
            "responseHashes": [
                "e3b0c44298fc1c149afbf4c8996fb92427ae41e4649b934ca495991b7852b855"
            ],
            "type": "Image",
            "firstPartyCookies": {},
            "firstPartyCookiesSent": {},
            "exampleSites": [
                "community.spiceworks.com",
                "cplusplus.com",
                "doctor.webmd.com",
                "gamefaqs.gamespot.com",
                "healthfully.com",
                "mashable.com",
                "tabs.ultimate-guitar.com",
                "www.allrecipes.com",
                "www.buzzfeed.com",
                "www.drugs.com",
                "endante.com",
                "hardwaretester.com",
                "www.lyricsmode.com",
                "www.acronymfinder.com",
                "10minutemail.com",
                "www.thinkbabynames.com",
                "paddling.com",
                "www.rxlist.com",
                "www.gamingdeputy.com",
                "www.realsimple.com"
            ]
        },
        {
            "rule": "a-mx\\.com\\/set",
            "cookies": 0.00292,
            "fingerprinting": 0,
            "subdomains": [
                "id"
            ],
            "apis": {},
            "sites": 30,
            "prevalence": 0.00302,
            "cnames": [],
            "responseHashes": [
                "38ab6c5ed4236c5df2eabd35e2c371396166203219f0117605b1938354f51a38",
                "05bccdeba20c947d2daaddf3c1b5a22fb65d8483af8a641759b9e1d6df41cb1b",
                "03f0b917fcfa876e24c8edc8a6ffae7c0f0e70e9e73d4af8b8e67767297fe14c",
                "cf716823a6a83fcdeb09b25c13273bf0dd236d37b5d411eb88948a8e10d7dfe4",
                "6fe6bf258356ed84ac7357167a874d7f46ee6b6f66ac17d24043b5068b5af1cd",
                "3e00819aa72d60d4618de5b5ce373b8eaf713d2fb3c45215631844babd823bc5",
                "b06457f5e2c120057210a0412fa5264a9fbb5bd8486d90c740b9255fe435a2d1",
                "6c4ec3ce0b624b44f1c7e79390120e8269e9aa41c3cb5014a46158891b26e24a",
                "8d18365f9607a20ff3326ff8efe1af7723043af1a68bc564ee7a715c53d7f110",
                "ea13622dde2f5b51b6b9f6659e23a7ec960d6d002bf76bc9ad32e52e233484aa",
                "ddcf4bf09c08c492ce62ae7a18b5aeb1d43744cee5fd3ff6226b6c640eeea71a",
                "b22d14cd59b2c2db2a65044fec4d1632a1075166a726ff3e38979bde20b2d8c0",
                "aa2c03e8c24373772024de32c490605fca75e443559131543c913b26432b4ccf",
                "d3a2199cac58dcbb626312149567b0c37aabe505f118b6b7b46cbbdb5dbf2e49",
                "09b7654d8597ab1e72eb53c15b70a1df19d9719aa48508537e05061953a65f9c",
                "771d738a0f43d21473f569c04aea047a5bdeea2da93507ca1b252def20697ddc",
                "bcee8bf2b1f9747cd51fe91f09b9311daedc92840f1ee913ab2651a05ee9b99f",
                "88e7d463bcf39458fd01398b18565ad2ca3a726636829baceb4680a798cd7503",
                "df5daa1b254eef2ee76f2967f32b3bad319939da939d251c560f891aeafa8cc1",
                "134518472d9e9e110619e27b0d91384ae81f6087c3658eb7596f9dd78d12d7fd",
                "d2ca373843ac09f32c539be7a1a1377d95b21622d7e14fdc96ceb213cdaaed52",
                "8944f94f51615fafc76a0adaf9c58a2e3f03e6eccd02a06ca82e4cdd758921c8",
                "a544d4a3bebb472dc53f5f95d825c45a8c7a239e6afaa444f982aa984e15c67d"
            ],
            "type": "Fetch",
            "firstPartyCookies": {},
            "firstPartyCookiesSent": {},
            "exampleSites": [
                "healthfully.com",
                "www.pcworld.com",
                "www.techadvisor.com",
                "www.jpost.com",
                "www.metrotimes.com",
                "www.pythontutorial.net",
                "www.primewire.tf",
                "www.sofascore.com",
                "realgm.com",
                "timesofindia.indiatimes.com",
                "greenwichmeantime.com",
                "copypastatext.com",
                "thetvdb.com",
                "www.mid-day.com",
                "downloads.digitaltrends.com",
                "justthenews.com",
                "macleans.ca",
                "diablo.fandom.com",
                "borderlands.fandom.com",
                "segmentnext.com"
            ]
        },
        {
            "rule": "a-mx\\.com\\/sync\\/",
            "cookies": 0.000504,
            "fingerprinting": 0,
            "subdomains": [
                "id"
            ],
            "apis": {},
            "sites": 8,
            "prevalence": 0.000806,
            "cnames": [],
            "responseHashes": [],
            "type": "XHR",
            "firstPartyCookies": {},
            "firstPartyCookiesSent": {
                "lotame_domain_check": 0.00020147073637554144
            },
            "exampleSites": [
                "picuki.me",
                "readcomiconline.li",
                "whatreallyhappened.com",
                "ww3.readjujutsukaisen.com",
                "www.gmanetwork.com",
                "www.pixwox.com",
                "www.politifact.com",
                "www.yogapedia.com"
            ]
        }
    ],
    "categories": [],
    "performance": {},
    "cookies": 0.019,
    "topInitiators": [
        {
            "domain": "a-mo.net",
            "prevalence": 0.5139318885448917
        },
        {
            "domain": "minutemedia-prebid.com",
            "prevalence": 0.13003095975232198
        },
        {
            "domain": "adapex.io",
            "prevalence": 0.0804953560371517
        },
        {
            "domain": "first party",
            "prevalence": 0.05263157894736842
        },
        {
            "domain": "h12-media.com",
            "prevalence": 0.034055727554179564
        },
        {
            "domain": "vuukle.com",
            "prevalence": 0.02786377708978328
        },
        {
            "domain": "adligature.com",
            "prevalence": 0.018575851393188854
        },
        {
            "domain": "script.ac",
            "prevalence": 0.018575851393188854
        },
        {
            "domain": "increaserev.com",
            "prevalence": 0.018575851393188854
        },
        {
            "domain": "vlitag.com",
            "prevalence": 0.015479876160990712
        }
    ],
    "types": {
        "Fetch": 115,
        "Image": 163,
        "XHR": 8
    },
    "nameservers": [
        "kiki.bunny.net",
        "coco.bunny.net"
    ]
}