{
    "domain": "12vod-adaptive.akamaized.net",
    "owner": {
        "name": "Akamai Technologies",
        "displayName": "Akamai",
        "privacyPolicy": "https://www.akamai.com/us/en/privacy-policies/",
        "url": "http://akamai.com"
    },
    "source": [
        "DuckDuckGo-NL"
    ],
    "prevalence": 0.000101,
    "sites": 1,
    "subdomains": [],
    "cnames": [],
    "fingerprinting": 0,
    "resources": [
        {
            "rule": "12vod-adaptive\\.akamaized\\.net\\/exp=1704256297~acl=%2F953faec7-4d1b-4809-bbf5-0feab188088b%2F%2A~hmac=2d473185b93b91dee89396e6a54c3b201ac0b20b6503fa21999c1f8011cec7ff\\/953faec7-4d1b-4809-bbf5-0feab188088b\\/parcel\\/audio\\/a76e143b\\.mp4",
            "cookies": 0.000201,
            "fingerprinting": 0,
            "subdomains": [],
            "apis": {},
            "sites": 2,
            "prevalence": 0.000201,
            "cnames": [],
            "responseHashes": [
                "6b673c6777b9ba0850ba7d3dd0828fdebf860c9182eab42b476630aa0d4bf89f"
            ],
            "type": "XHR",
            "firstPartyCookies": {},
            "firstPartyCookiesSent": {},
            "exampleSites": [
                "samsonite.nl",
                "www.samsonite.nl"
            ]
        }
    ],
    "categories": [
        "CDN"
    ],
    "performance": {},
    "cookies": 0.000101,
    "topInitiators": [
        {
            "domain": "vimeocdn.com",
            "prevalence": 1
        }
    ],
    "types": {
        "XHR": 2
    },
    "nameservers": []
}