{
    "domain": "3lift.com",
    "owner": {
        "name": "TripleLift",
        "displayName": "TripleLift",
        "privacyPolicy": "https://triplelift.com/privacy/",
        "url": "http://triplelift.com"
    },
    "source": [
        "DuckDuckGo-NL"
    ],
    "prevalence": 0.013,
    "sites": 129,
    "subdomains": [
        "eb2",
        "tlx",
        "dmpsync"
    ],
    "cnames": [],
    "fingerprinting": 0,
    "resources": [
        {
            "rule": "3lift\\.com\\/getuid",
            "cookies": 0,
            "fingerprinting": 0,
            "subdomains": [
                "eb2"
            ],
            "apis": {},
            "sites": 4,
            "prevalence": 0.000402,
            "cnames": [],
            "responseHashes": [
                "e3b0c44298fc1c149afbf4c8996fb92427ae41e4649b934ca495991b7852b855"
            ],
            "type": "Document",
            "firstPartyCookies": {},
            "firstPartyCookiesSent": {},
            "exampleSites": [
                "9to5mac.com",
                "electrek.co",
                "nl.automobiledimension.com",
                "www.picuki.com"
            ]
        },
        {
            "rule": "3lift\\.com\\/xuid",
            "cookies": 0.000503,
            "fingerprinting": 0,
            "subdomains": [
                "eb2"
            ],
            "apis": {},
            "sites": 67,
            "prevalence": 0.00673,
            "cnames": [],
            "responseHashes": [
                "05e6e6dab50a2ed29baa52bb9cd3d88afa3c5392fb53c2ac026c8d316da72a32"
            ],
            "type": "Image",
            "firstPartyCookies": {},
            "firstPartyCookiesSent": {
                "cookies.js": 0.0001005126143330988,
                "_kuid_": 0.0001005126143330988
            },
            "exampleSites": [
                "draxe.com",
                "www.alibaba.com",
                "www.cargurus.com",
                "www.fjallraven.com",
                "www.ventilatieshop.com",
                "www.directlampen.nl",
                "www.vitaminesperpost.nl",
                "www.nerdwallet.com",
                "www.apmex.com",
                "www.easeus.com",
                "www.jeroenbeekman.nl",
                "www.aliexpress.com",
                "www.green-acres.fr",
                "werkenbijdefensie.nl",
                "flinders.nl",
                "www.autohopper.nl",
                "www.hellotech.com",
                "www.uitagendarotterdam.nl",
                "www.biggreenegg.eu",
                "www.bouwmaat.nl"
            ]
        },
        {
            "rule": "3lift\\.com\\/header\\/auction",
            "cookies": 0.000503,
            "fingerprinting": 0,
            "subdomains": [
                "tlx"
            ],
            "apis": {},
            "sites": 31,
            "prevalence": 0.00312,
            "cnames": [],
            "responseHashes": [
                "0535c3bb3a17e4ac0fb7d29214d2181275662129dc2bdd2a89c35934e9fc5ba5"
            ],
            "type": "XHR",
            "firstPartyCookies": {},
            "firstPartyCookiesSent": {
                "lotame_domain_check": 0.0012061513719971856
            },
            "exampleSites": [
                "myanimelist.net",
                "slate.com",
                "www.accuweather.com",
                "www.dictionary.com",
                "www.digitaltrends.com",
                "www.ign.com",
                "www.mapquest.com",
                "www.thesaurus.com",
                "forum.audiogon.com",
                "www.computerworld.com",
                "www.denofgeek.com",
                "player.fm",
                "insideevs.com",
                "www.pravda.com.ua",
                "www.smh.com.au",
                "nl.ign.com",
                "strategywiki.org",
                "www.investing.com",
                "songmeanings.com",
                "www.timesofisrael.com"
            ]
        },
        {
            "rule": "3lift\\.com\\/sync",
            "cookies": 0.000302,
            "fingerprinting": 0,
            "subdomains": [
                "eb2"
            ],
            "apis": {},
            "sites": 39,
            "prevalence": 0.00392,
            "cnames": [],
            "responseHashes": [
                "05e6e6dab50a2ed29baa52bb9cd3d88afa3c5392fb53c2ac026c8d316da72a32"
            ],
            "type": "Document",
            "firstPartyCookies": {},
            "firstPartyCookiesSent": {},
            "exampleSites": [
                "www.dictionary.com",
                "www.dailydot.com",
                "www.smh.com.au",
                "strategywiki.org",
                "www.timesofisrael.com",
                "bbq-junkie.nl",
                "ejje.weblio.jp",
                "imgur.com",
                "www.denofgeek.com",
                "forum.audiogon.com",
                "appleinsider.com",
                "www.kids-n-fun.nl",
                "www.koreaboo.com",
                "www.avsim.com",
                "www.speeleiland.nl",
                "www.vulture.com",
                "songmeanings.com",
                "www.futbin.com",
                "www.immowelt.de",
                "www.haaretz.com"
            ]
        },
        {
            "rule": "3lift\\.com\\/header\\/auction",
            "cookies": 0.000302,
            "fingerprinting": 0,
            "subdomains": [
                "tlx"
            ],
            "apis": {},
            "sites": 30,
            "prevalence": 0.00302,
            "cnames": [],
            "responseHashes": [
                "0535c3bb3a17e4ac0fb7d29214d2181275662129dc2bdd2a89c35934e9fc5ba5"
            ],
            "type": "Fetch",
            "firstPartyCookies": {},
            "firstPartyCookiesSent": {
                "_li_dcdm_c": 0.0001005126143330988,
                "lotame_domain_check": 0.0011056387576640868
            },
            "exampleSites": [
                "community.spiceworks.com",
                "www.bustle.com",
                "www.dailydot.com",
                "www.nbcnews.com",
                "www.politico.com",
                "www.mindbodygreen.com",
                "www.deaandeelhouder.nl",
                "mydramalist.com",
                "www.koreaboo.com",
                "shellshock.io",
                "www.postgresqltutorial.com",
                "www.xxlmag.com",
                "bbq-junkie.nl",
                "www.mysqltutorial.org",
                "www.sqlitetutorial.net",
                "www.inverse.com",
                "www.kids-n-fun.nl",
                "nymag.com",
                "www.immowelt.de",
                "www.msnbc.com"
            ]
        },
        {
            "rule": "3lift\\.com\\/sync",
            "cookies": 0,
            "fingerprinting": 0,
            "subdomains": [
                "eb2"
            ],
            "apis": {},
            "sites": 12,
            "prevalence": 0.00121,
            "cnames": [],
            "responseHashes": [
                "05e6e6dab50a2ed29baa52bb9cd3d88afa3c5392fb53c2ac026c8d316da72a32"
            ],
            "type": "Image",
            "firstPartyCookies": {},
            "firstPartyCookiesSent": {},
            "exampleSites": [
                "spiceworks.com",
                "mydramalist.com",
                "myanimelist.net",
                "nl.ign.com",
                "uk.pcmag.com",
                "www.bustle.com",
                "www.ebaumsworld.com",
                "www.elitedaily.com",
                "www.ign.com",
                "www.inverse.com",
                "www.mapquest.com",
                "www.mindbodygreen.com"
            ]
        },
        {
            "rule": "3lift\\.com\\/ebda",
            "cookies": 0.000402,
            "fingerprinting": 0,
            "subdomains": [
                "eb2"
            ],
            "apis": {},
            "sites": 5,
            "prevalence": 0.000503,
            "cnames": [],
            "responseHashes": [
                "05e6e6dab50a2ed29baa52bb9cd3d88afa3c5392fb53c2ac026c8d316da72a32"
            ],
            "type": "Image",
            "firstPartyCookies": {},
            "firstPartyCookiesSent": {},
            "exampleSites": [
                "how2shout.com",
                "linux.how2shout.com",
                "www.avsim.com",
                "www.culinea.nl",
                "www.picuki.com"
            ]
        },
        {
            "rule": "3lift\\.com\\/sync\\/google\\/demand",
            "cookies": 0.000402,
            "fingerprinting": 0,
            "subdomains": [
                "eb2"
            ],
            "apis": {},
            "sites": 4,
            "prevalence": 0.000402,
            "cnames": [],
            "responseHashes": [],
            "type": "Image",
            "firstPartyCookies": {},
            "firstPartyCookiesSent": {},
            "exampleSites": [
                "how2shout.com",
                "www.avsim.com",
                "www.culinea.nl",
                "www.picuki.com"
            ]
        },
        {
            "rule": "3lift\\.com\\/getuid",
            "cookies": 0.000201,
            "fingerprinting": 0,
            "subdomains": [
                "eb2",
                "dmpsync"
            ],
            "apis": {},
            "sites": 3,
            "prevalence": 0.000302,
            "cnames": [],
            "responseHashes": [],
            "type": "Image",
            "firstPartyCookies": {},
            "firstPartyCookiesSent": {},
            "exampleSites": [
                "picuki.com",
                "www.smh.com.au",
                "www.speeleiland.nl"
            ]
        }
    ],
    "categories": [
        "Ad Motivated Tracking",
        "Advertising"
    ],
    "performance": {},
    "cookies": 0.00171,
    "topInitiators": [
        {
            "domain": "criteo.com",
            "prevalence": 0.21238938053097345
        },
        {
            "domain": "first party",
            "prevalence": 0.10176991150442478
        },
        {
            "domain": "vlitag.com",
            "prevalence": 0.035398230088495575
        },
        {
            "domain": "stpd.cloud",
            "prevalence": 0.035398230088495575
        },
        {
            "domain": "adform.net",
            "prevalence": 0.030973451327433628
        },
        {
            "domain": "amazon-adsystem.com",
            "prevalence": 0.030973451327433628
        },
        {
            "domain": "rubiconproject.com",
            "prevalence": 0.030973451327433628
        },
        {
            "domain": "script.ac",
            "prevalence": 0.030973451327433628
        },
        {
            "domain": "anyclip.com",
            "prevalence": 0.030973451327433628
        },
        {
            "domain": "staticneo.com",
            "prevalence": 0.02654867256637168
        }
    ],
    "types": {
        "Document": 43,
        "Image": 91,
        "XHR": 31,
        "Fetch": 30
    },
    "nameservers": [
        "ns-131.awsdns-16.com",
        "ns-814.awsdns-37.net",
        "ns-1640.awsdns-13.co.uk",
        "ns-1435.awsdns-51.org"
    ]
}